RobotFrameworkPercy/RobotFrameworkPercy.py
RobotFrameworkPercy/__init__.py
robot_framework_percy-0.1.1.dist-info/LICENSE
robot_framework_percy-0.1.1.dist-info/METADATA
robot_framework_percy-0.1.1.dist-info/WHEEL
robot_framework_percy-0.1.1.dist-info/top_level.txt
robot_framework_percy-0.1.1.dist-info/RECORD
