Metadata-Version: 2.1
Name: robot-framework-percy
Version: 0.1.1
Summary: Robot framework Percy client
Home-page: https://github.com/Minh0001/robot-framework-percy
Author: Minh Le
Author-email: quangminh0001@gmail.com
License: MIT
Platform: UNKNOWN
Classifier: Development Status :: 3 - Alpha
Classifier: Intended Audience :: Developers
Classifier: License :: OSI Approved :: MIT License
